DockQ/__main__.py
DockQ/operations.cpython-313-x86_64-linux-gnu.so
DockQ/operations_nocy.py
DockQ/constants.py
DockQ/parsers.py
DockQ/DockQ.py
DockQ/__init__.py
DockQ/operations.c
dockq-2.1.2.dist-info/METADATA
dockq-2.1.2.dist-info/top_level.txt
dockq-2.1.2.dist-info/entry_points.txt
dockq-2.1.2.dist-info/RECORD
dockq-2.1.2.dist-info/LICENSE
dockq-2.1.2.dist-info/WHEEL
