Metadata-Version: 2.1
Name: dockq
Version: 2.1.2
Summary: A Quality Measure for Protein, Nucleic Acids and Small Ligand Docking Models
Author-email: Claudio Mirabello <claudio.mirabello@scilifelab.se>, Bjorn Wallner <bjorn.wallner@liu.se>
Project-URL: Homepage, https://github.com/bjornwallner/DockQ
Project-URL: Issues, https://github.com/bjornwallner/DockQ/issues
Classifier: Programming Language :: Python :: 3
Classifier: License :: OSI Approved :: MIT License
Classifier: Operating System :: OS Independent
Requires-Python: >=3.8
License-File: LICENSE
Requires-Dist: numpy <2.0
Requires-Dist: biopython >=1.79
Requires-Dist: networkx
Requires-Dist: parallelbar
